ghoshtools/__init__.py
ghoshtools/extract_method.py
ghoshtools/ghoshtools.py
ghoshtools/globals.py
ghoshtools/utils.py
ghoshtools/resources/nextflow.config
ghoshtools/resources/nextflow_helper_script.py
ghoshtools/resources/poop.yml
ghoshtools/resources/run_python_function.nf
ghoshtools/resources/run_python_function_batched.nf
ghoshtools-0.1.0.dist-info/AUTHORS.rst
ghoshtools-0.1.0.dist-info/LICENSE
ghoshtools-0.1.0.dist-info/METADATA
ghoshtools-0.1.0.dist-info/WHEEL
ghoshtools-0.1.0.dist-info/top_level.txt
ghoshtools-0.1.0.dist-info/RECORD
