Metadata-Version: 2.1
Name: ghoshtools
Version: 0.1.0
Summary: Tools for the Ghosh.
Home-page: https://github.com/rghosh670/ghoshtools
Author: Rohit Ghosh
Author-email: rohit.ghosh@yale.edu
License: MIT license
Keywords: ghoshtools
Classifier: Development Status :: 2 - Pre-Alpha
Classifier: Intended Audience :: Developers
Classifier: License :: OSI Approved :: MIT License
Classifier: Natural Language :: English
Classifier: Programming Language :: Python :: 3
Classifier: Programming Language :: Python :: 3.6
Classifier: Programming Language :: Python :: 3.7
Classifier: Programming Language :: Python :: 3.8
Requires-Python: >=3.6
License-File: LICENSE
License-File: AUTHORS.rst
Requires-Dist: dill ==0.3.8
Requires-Dist: icecream ==2.1.3
Requires-Dist: pandas ==2.2.2
Requires-Dist: setuptools >69.1.1
